{
  "dependencies": {
    "extended_address": "street_address",
    "post_office_box": "street_address"
  },
  "description": "An Address following the convention of http://microformats.org/wiki/hcard",
  "properties": {
    "address": {
      "items": "string",
      "type": "array"
    },
    "country_name": {
      "required": true,
      "type": "string"
    },
    "extended_address": {
      "type": "string"
    },
    "locality": {
      "required": true,
      "type": "string"
    },
    "post_office_box": {
      "type": "string"
    },
    "postal_code": {
      "type": "string"
    },
    "region": {
      "required": true,
      "type": "string"
    },
    "street_address": {
      "type": "string"
    }
  },
  "type": "object"
}
